{"service_id":"BS02_TS02_JTBC","service_type":"stream_conditioning","config_version":"11.4.0","config":{"id":"BS02_TS02_JTBC","connection":{"mode":"external","esamVersion":"2013","healthCheck":false,"expectNotifications":true,"endPoints":[{"id":"BS02_02_TC01","signalAcquisitions":[{"url":"http://192.168.21.11:8080/api/esam/LiveEncodings/BS02_02","listeningPath":"/"},{"url":"http://192.168.21.36:8080/api/esam/LiveEncodings/BS02_02","listeningPath":"/"}],"networkName":"BS02_02","zoneIdentity":"TC01","dataId":"9104137bf30f413a9dcc524e"}],"type":"esam"},"timings":{"eventExpirationDelay":60,"prepareDelayForPlayRequest":1,"eventPrerollDelay":1,"prepareDelayForSelectInput":1}}}