{"service_id":"BS10_TS05_MBC_ChangWon","service_type":"stream_conditioning","config_version":"11.4.0","config":{"id":"BS10_TS05_MBC_ChangWon","connection":{"mode":"external","esamVersion":"2013","healthCheck":false,"expectNotifications":true,"endPoints":[{"id":"BS10_05_TC09","signalAcquisitions":[{"url":"http://192.168.21.19:8080/api/esam/LiveEncodings/BS10_05","listeningPath":"/"},{"url":"http://192.168.21.44:8080/api/esam/LiveEncodings/BS10_05","listeningPath":"/"}],"networkName":"BS10_05","zoneIdentity":"TC09","dataId":"231b137a0f2d401f859b1295"}],"type":"esam"},"timings":{"eventExpirationDelay":60,"prepareDelayForPlayRequest":1,"eventPrerollDelay":1,"prepareDelayForSelectInput":1}}}